{
    "bean": {
        "_v": 0,
        "addr": "r.apphone.sbs",
        "name": "رایگان | REALITY | @iP_CF | DE🇩🇪 | 0️⃣3️⃣",
        "pass": "c06434a8-2d86-4d21-a3ca-794900984dc3",
        "port": 2083,
        "stream": {
            "ed_len": 0,
            "insecure": false,
            "mux_s": 0,
            "net": "grpc",
            "pbk": "qfCtqrHzFktFcIj4h73KUS5KdYzcMsXKa7I0dWWxUmM",
            "sec": "tls",
            "sid": "20dd5999",
            "sni": "www.sourceforge.net",
            "utls": "firefox"
        }
    },
    "gid": 1,
    "id": 7061,
    "traffic": {
        "dl": 0,
        "ul": 0
    },
    "type": "vless",
    "yc": 653
}
